aliyunsdkeas/__init__.py
aliyunsdkeas/endpoint.py
aliyunsdkeas/request/__init__.py
aliyunsdkeas/request/v20210701/CommitServiceRequest.py
aliyunsdkeas/request/v20210701/CreateAppServiceRequest.py
aliyunsdkeas/request/v20210701/CreateBenchmarkTaskRequest.py
aliyunsdkeas/request/v20210701/CreateGatewayIntranetLinkedVpcRequest.py
aliyunsdkeas/request/v20210701/CreateGatewayRequest.py
aliyunsdkeas/request/v20210701/CreateResourceInstancesRequest.py
aliyunsdkeas/request/v20210701/CreateResourceLogRequest.py
aliyunsdkeas/request/v20210701/CreateResourceRequest.py
aliyunsdkeas/request/v20210701/CreateServiceAutoScalerRequest.py
aliyunsdkeas/request/v20210701/CreateServiceCronScalerRequest.py
aliyunsdkeas/request/v20210701/CreateServiceMirrorRequest.py
aliyunsdkeas/request/v20210701/CreateServiceRequest.py
aliyunsdkeas/request/v20210701/DeleteBenchmarkTaskRequest.py
aliyunsdkeas/request/v20210701/DeleteGatewayIntranetLinkedVpcRequest.py
aliyunsdkeas/request/v20210701/DeleteGatewayRequest.py
aliyunsdkeas/request/v20210701/DeleteResourceDLinkRequest.py
aliyunsdkeas/request/v20210701/DeleteResourceInstancesRequest.py
aliyunsdkeas/request/v20210701/DeleteResourceLogRequest.py
aliyunsdkeas/request/v20210701/DeleteResourceRequest.py
aliyunsdkeas/request/v20210701/DeleteServiceAutoScalerRequest.py
aliyunsdkeas/request/v20210701/DeleteServiceCronScalerRequest.py
aliyunsdkeas/request/v20210701/DeleteServiceInstancesRequest.py
aliyunsdkeas/request/v20210701/DeleteServiceLabelRequest.py
aliyunsdkeas/request/v20210701/DeleteServiceMirrorRequest.py
aliyunsdkeas/request/v20210701/DeleteServiceRequest.py
aliyunsdkeas/request/v20210701/DescribeBenchmarkTaskReportRequest.py
aliyunsdkeas/request/v20210701/DescribeBenchmarkTaskRequest.py
aliyunsdkeas/request/v20210701/DescribeGatewayRequest.py
aliyunsdkeas/request/v20210701/DescribeGroupRequest.py
aliyunsdkeas/request/v20210701/DescribeResourceDLinkRequest.py
aliyunsdkeas/request/v20210701/DescribeResourceLogRequest.py
aliyun_python_sdk_eas-0.0.9.dist-info/LICENSE
aliyun_python_sdk_eas-0.0.9.dist-info/METADATA
aliyun_python_sdk_eas-0.0.9.dist-info/WHEEL
aliyun_python_sdk_eas-0.0.9.dist-info/top_level.txt
aliyun_python_sdk_eas-0.0.9.dist-info/RECORD
